factrainer/base/__init__.py
factrainer/base/config.py
factrainer/base/dataset.py
factrainer/base/py.typed
factrainer/base/raw_model.py
factrainer_base-0.1.27.dist-info/METADATA
factrainer_base-0.1.27.dist-info/WHEEL
factrainer_base-0.1.27.dist-info/RECORD
